MANIFEST.in
NEWS.rst
README.rst
pkginfo.py
setup.py
src/django_skylark.egg-info/PKG-INFO
src/django_skylark.egg-info/SOURCES.txt
src/django_skylark.egg-info/dependency_links.txt
src/django_skylark.egg-info/not-zip-safe
src/django_skylark.egg-info/requires.txt
src/django_skylark.egg-info/top_level.txt
src/skylark/__init__.py
src/skylark/assembly.py
src/skylark/chirp.py
src/skylark/context_processors.py
src/skylark/cssimgreplace.py
src/skylark/instructions.py
src/skylark/page.py
src/skylark/snippet.py
src/skylark/templatepatch.py
src/skylark/conf/__init__.py
src/skylark/conf/default.py
src/skylark/management/__init__.py
src/skylark/management/commands/__init__.py
src/skylark/management/commands/crunchypage.py
src/skylark/management/commands/messages.py
src/skylark/plans/__init__.py
src/skylark/plans/base.py
src/skylark/plans/fewest.py
src/skylark/plans/reusable.py
src/skylark/plans/separate.py
src/skylark/processor/__init__.py
src/skylark/processor/clevercss.py
src/skylark/renderer/__init__.py
src/skylark/renderer/base.py
src/skylark/renderer/html.py
src/skylark/renderer/xhtml.py
src/skylark/templates/chirp/tools.yaml
src/skylark/templates/chirp/media/dojo/AdapterRegistry.js
src/skylark/templates/chirp/media/dojo/DeferredList.js
src/skylark/templates/chirp/media/dojo/LICENSE
src/skylark/templates/chirp/media/dojo/NodeList-data.js
src/skylark/templates/chirp/media/dojo/NodeList-fx.js
src/skylark/templates/chirp/media/dojo/NodeList-html.js
src/skylark/templates/chirp/media/dojo/NodeList-manipulate.js
src/skylark/templates/chirp/media/dojo/NodeList-traverse.js
src/skylark/templates/chirp/media/dojo/OpenAjax.js
src/skylark/templates/chirp/media/dojo/Stateful.js
src/skylark/templates/chirp/media/dojo/_base.js
src/skylark/templates/chirp/media/dojo/back.js
src/skylark/templates/chirp/media/dojo/behavior.js
src/skylark/templates/chirp/media/dojo/build.txt
src/skylark/templates/chirp/media/dojo/cache.js
src/skylark/templates/chirp/media/dojo/colors.js
src/skylark/templates/chirp/media/dojo/cookie.js
src/skylark/templates/chirp/media/dojo/currency.js
src/skylark/templates/chirp/media/dojo/date.js
src/skylark/templates/chirp/media/dojo/dojo.js
src/skylark/templates/chirp/media/dojo/dojo.js.uncompressed.js
