Metadata-Version: 1.0
Name: django-skylark
Version: 0.4.3
Summary: UNKNOWN
Home-page: http://robmadole.com
Author: Rob Madole
Author-email: robmadole@gmail.com
License: BSD
Keywords: web 2 html css mvc django dojo yaml
Platform: UNKNOWN
